pine/__init__.py
pine/__init__.pyr
pine/app.py
pine/cli.py
pine/exceptions.py
pine/pine.py
pine/commands/__init__.py
pine/commands/config.py
pine/commands/git.py
pine/commands/install.py
pine/commands/make.py
pine/commands/setup.py
pine/commands/update.py
pine/commands/utils.py
pine/config/__init__.py
pine/config/common_site_config.py
pine/config/lets_encrypt.py
pine/config/nginx.py
pine/config/procfile.py
pine/config/production_setup.py
pine/config/redis.py
pine/config/site_config.py
pine/config/supervisor.py
pine/config/systemd.py
pine/config/templates/502.html
pine/config/templates/Procfile
pine/config/templates/guipine_nginx.conf
pine/config/templates/letsencrypt.cfg
pine/config/templates/melon_sudoers
pine/config/templates/nginx.conf
pine/config/templates/nginx_default.conf
pine/config/templates/redis_cache.conf
pine/config/templates/redis_queue.conf
pine/config/templates/supervisor.conf
pine/config/templates/systemd/pimelon-melon-default-worker.service
pine/config/templates/systemd/pimelon-melon-long-worker.service
pine/config/templates/systemd/pimelon-melon-schedule.service
pine/config/templates/systemd/pimelon-melon-short-worker.service
pine/config/templates/systemd/pimelon-melon-web.service
pine/config/templates/systemd/pimelon-node-socketio.service
pine/config/templates/systemd/pimelon-redis-cache.service
pine/config/templates/systemd/pimelon-redis-queue.service
pine/config/templates/systemd/pimelon-redis.target
pine/config/templates/systemd/pimelon-web.target
pine/config/templates/systemd/pimelon-workers.target
pine/config/templates/systemd/pimelon.target
pine/patches/__init__.py
pine/patches/patches.txt
pine/patches/v6/__init__.py
pine/patches/v6/fix_backup_cronjob.py
pine/patches/v6/fix_user_permissions.py
pine/patches/v6/set_live_reload_config.py
pine/patches/v6/update_archived_sites.py
pine/playbooks/README.md
pine/playbooks/create_user.yml
pine/playbooks/macosx.yml
pine/playbooks/site.yml
pine/playbooks/vm_build.yml
pimelon-6.16.20.dist-info/METADATA
pimelon-6.16.20.dist-info/WHEEL
pimelon-6.16.20.dist-info/entry_points.txt
pimelon-6.16.20.dist-info/licenses/LICENSE
pimelon-6.16.20.dist-info/RECORD
