Metadata-Version: 2.4
Name: pimelon
Version: 6.16.20
Summary: CLI to manage Multi-tenant deployments for MonakERP Apps
Project-URL: Changelog, https://github.com/amonak/pine/releases
Project-URL: Documentation, https://docs.monakerp.com/docs/user/en/pine
Project-URL: Homepage, https://monakerp.com/pine
Project-URL: Source, https://github.com/amonak/pine
Author-email: Alphamonak Solutions <amonak@monakerp.com>
License-Expression: MIT
License-File: LICENSE
Classifier: Development Status :: 5 - Production/Stable
Classifier: Environment :: Console
Classifier: License :: OSI Approved :: GNU General Public License v3 (GPLv3)
Classifier: Natural Language :: English
Classifier: Operating System :: MacOS
Classifier: Operating System :: OS Independent
Classifier: Topic :: Software Development :: Build Tools
Classifier: Topic :: Software Development :: User Interfaces
Classifier: Topic :: System :: Installation/Setup
Requires-Python: >=3.8
Requires-Dist: click~=8.2.0
Requires-Dist: gitpython~=3.1.30
Requires-Dist: honcho
Requires-Dist: jinja2~=3.1.3
Requires-Dist: python-crontab~=2.6.0
Requires-Dist: requests~=2.32.3
Requires-Dist: semantic-version~=2.10.0
Requires-Dist: setuptools>=71.0.0
Requires-Dist: tomli; python_version < '3.11'
Requires-Dist: uv~=0.7.12
